{
    "status": 1,
    "msg": "",
    "list": [{
        "desc": "《人渣的本愿》这部新番黑马，从一开播就话题不断，到现在快要大结局了虐身虐心到不行，披着肉番讲真爱，开着车还要虐着心！者的一提的是，此次拍摄的四位COSER都是妹子！妹子！子！ By：安乐冈花火：莉莎www、粟屋麦：大佬大佬大佬君、钟井鸣海：_Novaaa、皆川茜：一个迷妹JOJOBABY。",
        "pvnum": "",
        "createdate": "2017-03-23 19:18:22",
        "scover": "http://img4.cache.netease.com/photo/0031/2017-03-23/s_CG82EN6A6LRK0031.jpg",
        "setname": "《人渣的本愿》的COSPLAY欣赏",
        "cover": "http://img3.cache.netease.com/photo/0031/2017-03-23/CG82EN6A6LRK0031.jpg",
        "pics": ["http://img3.cache.netease.com/photo/0031/2017-03-23/CG82EN6A6LRK0031.jpg", "http://img3.cache.netease.com/photo/0031/2017-03-23/CG82EN9Q6LRK0031.jpg", "http://img4.cache.netease.com/photo/0031/2017-03-23/CG82ENBI6LRK0031.jpg"],
        "clientcover1": "",
        "replynum": "17",
        "topicname": "",
        "setid": "92909",
        "seturl": "http://play.163.com/photoview/6LRK0031/92909.html",
        "datetime": "2017-03-23 19:19:30",
        "clientcover": "",
        "imgsum": "14",
        "tcover": "http://img4.cache.netease.com/photo/0031/2017-03-23/t_CG82EN6A6LRK0031.jpg"
    }, {
        "desc": "小编找到一组非常精美的尤娜Cos图片。尤娜是日本游戏制作商史克威尔艾尼克斯出品的电子游戏最终幻想系列第十部《Final Fantasy Ⅹ》（最终幻想Ⅹ）中的虚拟角色，女主角。",
        "pvnum": "",
        "createdate": "2017-03-22 18:26:00",
        "scover": "http://img4.cache.netease.com/photo/0031/2017-03-22/s_CG5D23OC6LRK0031.jpg",
        "setname": "《最终幻想》女神尤娜COS美翻 脸蛋身材满分",
        "cover": "http://img4.cache.netease.com/photo/0031/2017-03-22/CG5D23OC6LRK0031.jpg",
        "pics": ["http://img3.cache.netease.com/photo/0031/2017-03-22/CG5D23OC6LRK0031.jpg", "http://img4.cache.netease.com/photo/0031/2017-03-22/CG5D23QJ6LRK0031.jpg", "http://img3.cache.netease.com/photo/0031/2017-03-22/CG5D23SP6LRK0031.jpg"],
        "clientcover1": "",
        "replynum": "21",
        "topicname": "",
        "setid": "92883",
        "seturl": "http://play.163.com/photoview/6LRK0031/92883.html",
        "datetime": "2017-03-22 18:26:25",
        "clientcover": "",
        "imgsum": "7",
        "tcover": "http://img4.cache.netease.com/photo/0031/2017-03-22/t_CG5D23OC6LRK0031.jpg"
    }, {
        "desc": "《小林家的龙女仆》是由酷教信徒创作的漫画作品，于2013年5月在《月刊Action》上开始连载，2016年5月宣布动画化。",
        "pvnum": "",
        "createdate": "2017-03-21 21:31:31",
        "scover": "http://img3.cache.netease.com/photo/0031/2017-03-21/s_CG2DCK983S010031.jpg",
        "setname": "小林家的龙女仆cos by  洛霁无",
        "cover": "http://img3.cache.netease.com/photo/0031/2017-03-21/CG2DCK983S010031.jpg",
        "pics": ["http://img4.cache.netease.com/photo/0031/2017-03-21/CG2DCK983S010031.jpg", "http://img4.cache.netease.com/photo/0031/2017-03-21/CG2DCTCJ3S010031.jpg", "http://img3.cache.netease.com/photo/0031/2017-03-21/CG2DCQ7B3S010031.jpg"],
        "clientcover1": "",
        "replynum": "0",
        "topicname": "",
        "setid": "92874",
        "seturl": "http://play.163.com/photoview/6LRK0031/92874.html",
        "datetime": "2017-03-21 21:44:00",
        "clientcover": "",
        "imgsum": "15",
        "tcover": "http://img4.cache.netease.com/photo/0031/2017-03-21/t_CG2DCK983S010031.jpg"
    }, {
        "desc": "下面要推荐的是《阴阳师》“人形之舞——鬼女红叶”，与上期阎魔 X 判官的互撩日常不同——这组COS图略带了一丝阴森的气息。作者本人对于这套图的释义是：“这套人形之舞的设想是红叶在畸形的爱中被操控着舞蹈，而操控自己的提线者正是自己空荡饥渴的心，舞得越美越悲伤，喰的人心越多却越找不回自己的心。”",
        "pvnum": "",
        "createdate": "2017-03-17 17:21:11",
        "scover": "http://img3.cache.netease.com/photo/0031/2017-03-17/s_CFO50SQ43S010031.jpg",
        "setname": "人形之舞-鬼女红叶 by 走路摇",
        "cover": "http://img3.cache.netease.com/photo/0031/2017-03-17/CFO50SQ43S010031.jpg",
        "pics": ["http://img4.cache.netease.com/photo/0031/2017-03-17/CFO50SQ43S010031.jpg", "http://img3.cache.netease.com/photo/0031/2017-03-17/CFO5105P3S010031.jpg", "http://img3.cache.netease.com/photo/0031/2017-03-17/CFO510DJ3S010031.jpg"],
        "clientcover1": "",
        "replynum": "0",
        "topicname": "",
        "setid": "92829",
        "seturl": "http://play.163.com/photoview/6LRK0031/92829.html",
        "datetime": "2017-03-17 17:21:17",
        "clientcover": "",
        "imgsum": "16",
        "tcover": "http://img4.cache.netease.com/photo/0031/2017-03-17/t_CFO50SQ43S010031.jpg"
    }, {
        "desc": "这是一周Cosplay秀时刻，每周小编都会为大家推荐一些非常不错的Cosplay作品，本次推荐的作品包括：《灵魂武器》、《食戟之灵》等等。",
        "pvnum": "",
        "createdate": "2017-03-17 16:45:29",
        "scover": "http://img4.cache.netease.com/photo/0031/2017-03-17/s_CFO24BD43S010031.jpg",
        "setname": "一周精品Cosplay盘点：第96期",
        "cover": "http://img3.cache.netease.com/photo/0031/2017-03-17/CFO24BD43S010031.jpg",
        "pics": ["http://img4.cache.netease.com/photo/0031/2017-03-17/CFO24BD43S010031.jpg", "http://img4.cache.netease.com/photo/0031/2017-03-17/CFO249LF3S010031.jpg", "http://img4.cache.netease.com/photo/0031/2017-03-17/CFO24AAF3S010031.jpg"],
        "clientcover1": "",
        "replynum": "0",
        "topicname": "",
        "setid": "92823",
        "seturl": "http://play.163.com/photoview/6LRK0031/92823.html",
        "datetime": "2017-03-17 16:45:36",
        "clientcover": "",
        "imgsum": "21",
        "tcover": "http://img3.cache.netease.com/photo/0031/2017-03-17/t_CFO24BD43S010031.jpg"
    }, {
        "desc": "小编搜到一组《Fate》玛修的cos作品，玛修·基列莱特 cn: 鳗鱼霏儿",
        "pvnum": "",
        "createdate": "2017-03-15 19:20:41",
        "scover": "http://img4.cache.netease.com/photo/0031/2017-03-15/s_CFJFDELC6LRK0031.jpeg",
        "setname": "这样的学妹谁不想要?黑丝短裙清血槽",
        "cover": "http://img4.cache.netease.com/photo/0031/2017-03-15/CFJFDELC6LRK0031.jpeg",
        "pics": ["http://img3.cache.netease.com/photo/0031/2017-03-15/CFJFDELC6LRK0031.jpeg", "http://img3.cache.netease.com/photo/0031/2017-03-15/CFJFDESK6LRK0031.jpeg", "http://img4.cache.netease.com/photo/0031/2017-03-15/CFJFDF386LRK0031.jpeg"],
        "clientcover1": "",
        "replynum": "177",
        "topicname": "",
        "setid": "92792",
        "seturl": "http://play.163.com/photoview/6LRK0031/92792.html",
        "datetime": "2017-03-15 19:21:16",
        "clientcover": "",
        "imgsum": "15",
        "tcover": "http://img3.cache.netease.com/photo/0031/2017-03-15/t_CFJFDELC6LRK0031.jpeg"
    }, {
        "desc": "3月14日，魔导士影像工作室为爱玩网的读者们送上了一份贺礼。他们邀请了国内四位美女Coser——Cosplay终极变身冠军天诛焱、2016暴雪Cosplay大赛中国区亚军Mio十一、插画师兼Coser罐儿，以及美女主编小睡共同出镜，创作了一组为庆贺白色情人节为主题的创意拍摄，期盼在这美好一天里每位读者都可以获得甜蜜与幸福。",
        "pvnum": "",
        "createdate": "2017-03-14 18:51:22",
        "scover": "http://img3.cache.netease.com/photo/0031/2017-03-14/s_CFGF69FN3S010031.jpg",
        "setname": "魔导士出品：白色情人节四大游戏美女贺图",
        "cover": "http://img3.cache.netease.com/photo/0031/2017-03-14/CFGF69FN3S010031.jpg",
        "pics": ["http://img4.cache.netease.com/photo/0031/2017-03-14/CFGF69FN3S010031.jpg", "http://img4.cache.netease.com/photo/0031/2017-03-14/CFGF69QJ3S010031.jpg", "http://img3.cache.netease.com/photo/0031/2017-03-14/CFGF6A0C3S010031.jpg"],
        "clientcover1": "",
        "replynum": "0",
        "topicname": "",
        "setid": "92778",
        "seturl": "http://play.163.com/photoview/6LRK0031/92778.html",
        "datetime": "2017-03-14 18:51:26",
        "clientcover": "",
        "imgsum": "28",
        "tcover": "http://img3.cache.netease.com/photo/0031/2017-03-14/t_CFGF69FN3S010031.jpg"
    }, {
        "desc": "在光与影的交错中，COSER们都展示着他们自己心中《魔兽》本来的模样，灵动的精灵、踏实的人类，手握魔法奥秘的法师、充满力量圣骑士……",
        "pvnum": "",
        "createdate": "2017-03-13 16:58:43",
        "scover": "http://img3.cache.netease.com/photo/0031/2017-03-13/s_CFE2G49J6LRK0031.jpg",
        "setname": "《魔兽世界》精美COS 魅惑精灵秀小蛮腰",
        "cover": "http://img4.cache.netease.com/photo/0031/2017-03-13/CFE2G49J6LRK0031.jpg",
        "pics": ["http://img3.cache.netease.com/photo/0031/2017-03-13/CFE2G2LE6LRK0031.jpg", "http://img3.cache.netease.com/photo/0031/2017-03-13/CFE2G2NM6LRK0031.jpg", "http://img4.cache.netease.com/photo/0031/2017-03-13/CFE2G2QJ6LRK0031.jpg"],
        "clientcover1": "",
        "replynum": "6",
        "topicname": "",
        "setid": "92756",
        "seturl": "http://play.163.com/photoview/6LRK0031/92756.html",
        "datetime": "2017-03-13 16:59:25",
        "clientcover": "",
        "imgsum": "21",
        "tcover": "http://img3.cache.netease.com/photo/0031/2017-03-13/t_CFE2G49J6LRK0031.jpg"
    }, {
        "desc": "是一周Cosplay秀时刻，每周小编都会为大家推荐一些非常不错的Cosplay作品，本次推荐的作品包括：《初音未来》、《冰上的尤里》等等。",
        "pvnum": "",
        "createdate": "2017-03-10 17:02:07",
        "scover": "http://img4.cache.netease.com/photo/0031/2017-03-10/s_CF61ECK63S010031.jpg",
        "setname": "一周精品Cosplay盘点：第94期",
        "cover": "http://img3.cache.netease.com/photo/0031/2017-03-10/CF61ECK63S010031.jpg",
        "pics": ["http://img4.cache.netease.com/photo/0031/2017-03-10/CF61ECK63S010031.jpg", "http://img4.cache.netease.com/photo/0031/2017-03-10/CF61E5P63S010031.jpg", "http://img4.cache.netease.com/photo/0031/2017-03-10/CF61E8HI3S010031.jpg"],
        "clientcover1": "",
        "replynum": "0",
        "topicname": "",
        "setid": "92721",
        "seturl": "http://play.163.com/photoview/6LRK0031/92721.html",
        "datetime": "2017-03-10 18:32:21",
        "clientcover": "",
        "imgsum": "16",
        "tcover": "http://img3.cache.netease.com/photo/0031/2017-03-10/t_CF61ECK63S010031.jpg"
    }, {
        "desc": "今天，小编看到一组韩国COS团体RZ的作品，COS的是《御剑情缘》中的古装角色。这组COS还原度极高，从服装到发饰，还有手中的油纸伞，甚至连胸型都做到了完全还原。",
        "pvnum": "",
        "createdate": "2017-03-09 17:48:11",
        "scover": "http://img4.cache.netease.com/photo/0031/2017-03-09/s_CF3RP89V6LRK0031.jpg",
        "setname": "韩国妹子高还原古装COS:眼含春水",
        "cover": "http://img4.cache.netease.com/photo/0031/2017-03-09/CF3RP89V6LRK0031.jpg",
        "pics": ["http://img3.cache.netease.com/photo/0031/2017-03-09/CF3RP7VF6LRK0031.jpg", "http://img4.cache.netease.com/photo/0031/2017-03-09/CF3RP84P6LRK0031.jpg", "http://img4.cache.netease.com/photo/0031/2017-03-09/CF3RP87I6LRK0031.jpg"],
        "clientcover1": "",
        "replynum": "73",
        "topicname": "",
        "setid": "92702",
        "seturl": "http://play.163.com/photoview/6LRK0031/92702.html",
        "datetime": "2017-03-09 17:49:55",
        "clientcover": "",
        "imgsum": "23",
        "tcover": "http://img4.cache.netease.com/photo/0031/2017-03-09/t_CF3RP89V6LRK0031.jpg"
    }, {
        "desc": "《奥菲斯的故事》是一款以希腊神话为背景的韩国策略手机游戏，Q萌的画风和视觉小说般的游戏模式吸引了大量女性玩家。近日，螺旋猫成员Doremi就为大家带来了游戏女主角欧律狄刻的COS。小姐姐的丰乳肥臀白大腿，看了让人把持不住。",
        "pvnum": "",
        "createdate": "2017-03-09 17:40:02",
        "scover": "http://img3.cache.netease.com/photo/0031/2017-03-09/s_CF3RAB876LRK0031.jpg",
        "setname": "丰乳肥臀白皙大长腿 螺旋猫Doremi最新COS",
        "cover": "http://img3.cache.netease.com/photo/0031/2017-03-09/CF3RAB876LRK0031.jpg",
        "pics": ["http://img3.cache.netease.com/photo/0031/2017-03-09/CF3RAB876LRK0031.jpg", "http://img4.cache.netease.com/photo/0031/2017-03-09/CF3RABB56LRK0031.jpg", "http://img4.cache.netease.com/photo/0031/2017-03-09/CF3RABDJ6LRK0031.jpg"],
        "clientcover1": "",
        "replynum": "0",
        "topicname": "",
        "setid": "92701",
        "seturl": "http://play.163.com/photoview/6LRK0031/92701.html",
        "datetime": "2017-03-09 17:41:53",
        "clientcover": "",
        "imgsum": "9",
        "tcover": "http://img3.cache.netease.com/photo/0031/2017-03-09/t_CF3RAB876LRK0031.jpg"
    }, {
        "desc": "面瘫鼻祖级别的萌妹子小叽，在“走走路就能捡个老婆回家”这种超级后宫级故事情节中，小叽可以说是启蒙了无数宅男的热血。而这套COS作品中，COSER面瘫不做作演绎的很到位，那么一起来欣赏吧！小叽CN：Faerie、摄影:影十七、妆娘：郁荨、后期：狂暴兔子麦茶菌、姬友",
        "pvnum": "",
        "createdate": "2017-03-08 17:21:53",
        "scover": "http://img4.cache.netease.com/photo/0031/2017-03-08/s_CF17R2RI6LRK0031.jpg",
        "setname": "面瘫萌妹鼻祖 人形电脑天使心小叽的COS赏",
        "cover": "http://img4.cache.netease.com/photo/0031/2017-03-08/CF17R2RI6LRK0031.jpg",
        "pics": ["http://img4.cache.netease.com/photo/0031/2017-03-08/CF17R2RI6LRK0031.jpg", "http://img3.cache.netease.com/photo/0031/2017-03-08/CF17R2TS6LRK0031.jpg", "http://img4.cache.netease.com/photo/0031/2017-03-08/CF17R2VS6LRK0031.jpg"],
        "clientcover1": "",
        "replynum": "4",
        "topicname": "",
        "setid": "92680",
        "seturl": "http://play.163.com/photoview/6LRK0031/92680.html",
        "datetime": "2017-03-08 17:22:27",
        "clientcover": "",
        "imgsum": "13",
        "tcover": "http://img4.cache.netease.com/photo/0031/2017-03-08/t_CF17R2RI6LRK0031.jpg"
    }, {
        "desc": "《缘之空》的穹妹一直都是大家的初恋对象，也是COS届的宠儿。以其特有的小女孩欲拒还换的娇羞吸引这人们。近日，Coser零夜zeroo为我们带来了一组穹妹的泳装COS照。娇小的身材，懵懂的眼神，似乎又回到了初恋，贫乳也别有一番味道呢。",
        "pvnum": "",
        "createdate": "2017-03-07 17:03:41",
        "scover": "http://img3.cache.netease.com/photo/0031/2017-03-07/s_CEUKK9PK6LRK0031.jpg",
        "setname": "娇小可爱><性感穹妹泳装Cos美图欣赏",
        "cover": "http://img4.cache.netease.com/photo/0031/2017-03-07/CEUKK9PK6LRK0031.jpg",
        "pics": ["http://img3.cache.netease.com/photo/0031/2017-03-07/CEUKK9PK6LRK0031.jpg", "http://img4.cache.netease.com/photo/0031/2017-03-07/CEUKKA0L6LRK0031.jpg", "http://img4.cache.netease.com/photo/0031/2017-03-07/CEUKKA956LRK0031.jpg"],
        "clientcover1": "",
        "replynum": "158",
        "topicname": "",
        "setid": "92659",
        "seturl": "http://play.163.com/photoview/6LRK0031/92659.html",
        "datetime": "2017-03-07 17:08:30",
        "clientcover": "",
        "imgsum": "16",
        "tcover": "http://img3.cache.netease.com/photo/0031/2017-03-07/t_CEUKK9PK6LRK0031.jpg"
    }, {
        "desc": "《大话西游热血版》全平台公测火爆开启，四大种族再续经典！人魔仙鬼四大种族也将在全新即时制战斗中焕发异样光彩，高清coser美图今天首度曝光，",
        "pvnum": "",
        "createdate": "2017-03-06 17:16:59",
        "scover": "http://img3.cache.netease.com/photo/0031/2017-03-06/s_CES2RDB06LRK0031.jpg",
        "setname": "《大话西游热血版》coser美图曝光",
        "cover": "http://img4.cache.netease.com/photo/0031/2017-03-06/CES2RDB06LRK0031.jpg",
        "pics": ["http://img4.cache.netease.com/photo/0031/2017-03-06/CES2RDB06LRK0031.jpg", "http://img4.cache.netease.com/photo/0031/2017-03-06/CES2RDCQ6LRK0031.jpg", "http://img4.cache.netease.com/photo/0031/2017-03-06/CES2RDEB6LRK0031.jpg"],
        "clientcover1": "",
        "replynum": "0",
        "topicname": "",
        "setid": "92647",
        "seturl": "http://play.163.com/photoview/6LRK0031/92647.html",
        "datetime": "2017-03-06 17:19:45",
        "clientcover": "",
        "imgsum": "4",
        "tcover": "http://img3.cache.netease.com/photo/0031/2017-03-06/t_CES2RDB06LRK0031.jpg"
    }, {
        "desc": "随着《塞尔达传说：荒野之息》的问世，诸多周边或相关活动也已纷纷亮相，由Holly Wolf出演，Paul Hillier和Novii拍摄的了一组COS。话不多说，上图！",
        "pvnum": "",
        "createdate": "2017-03-06 10:43:40",
        "scover": "http://img4.cache.netease.com/photo/0031/2017-03-06/s_CERCA7Q06LRK0031.jpg",
        "setname": "塞尔达传说：荒野之息Cos by Holly Wolf",
        "cover": "http://img3.cache.netease.com/photo/0031/2017-03-06/CERCA7Q06LRK0031.jpg",
        "pics": ["http://img3.cache.netease.com/photo/0031/2017-03-06/CERCA7Q06LRK0031.jpg", "http://img3.cache.netease.com/photo/0031/2017-03-06/CERCA89G6LRK0031.jpg", "http://img4.cache.netease.com/photo/0031/2017-03-06/CERCA8OK6LRK0031.jpg"],
        "clientcover1": "",
        "replynum": "1",
        "topicname": "",
        "setid": "92636",
        "seturl": "http://play.163.com/photoview/6LRK0031/92636.html",
        "datetime": "2017-03-06 10:45:39",
        "clientcover": "",
        "imgsum": "16",
        "tcover": "http://img4.cache.netease.com/photo/0031/2017-03-06/t_CERCA7Q06LRK0031.jpg"
    }, {
        "desc": "说到低成本的cosplay，大家一定想到来自泰国的“Low Cost Cosplay”，他真是把创意玩到前无古人后无来者的人，但现今社会一旦你红了，想模仿或是也想跟你做一样事情的人肯定有，今天分享的这个“日版低成本cosplay”，我们就来看看推特玩家たかや(@tky888tky)有哪些惊人的表现吧！",
        "pvnum": "",
        "createdate": "2017-03-03 18:49:48",
        "scover": "http://img4.cache.netease.com/photo/0031/2017-03-03/s_CEKGSM5N6LRK0031.jpg",
        "setname": "日版低成本cosplay 创意加上耻力的完美组合",
        "cover": "http://img4.cache.netease.com/photo/0031/2017-03-03/CEKGSM5N6LRK0031.jpg",
        "pics": ["http://img3.cache.netease.com/photo/0031/2017-03-03/CEKGSM5N6LRK0031.jpg", "http://img3.cache.netease.com/photo/0031/2017-03-03/CEKGSM7N6LRK0031.jpg", "http://img4.cache.netease.com/photo/0031/2017-03-03/CEKGSMA16LRK0031.jpg"],
        "clientcover1": "",
        "replynum": "15",
        "topicname": "",
        "setid": "92622",
        "seturl": "http://play.163.com/photoview/6LRK0031/92622.html",
        "datetime": "2017-03-03 18:53:47",
        "clientcover": "",
        "imgsum": "15",
        "tcover": "http://img4.cache.netease.com/photo/0031/2017-03-03/t_CEKGSM5N6LRK0031.jpg"
    }, {
        "desc": "今天给大家带来了2017年美国Katsucon漫展Cosplay第一弹，小伙伴们来看看老外的cosplay，没有波涛胸涌，没有薄露透短，一样能整出这么高端的漫展。",
        "pvnum": "",
        "createdate": "2017-03-02 17:08:10",
        "scover": "http://img3.cache.netease.com/photo/0031/2017-03-02/s_CEHOM0SO6LRK0031.jpg",
        "setname": "2017美国Katsucon动漫展亮眼的Cos合集",
        "cover": "http://img4.cache.netease.com/photo/0031/2017-03-02/CEHOM0SO6LRK0031.jpg",
        "pics": ["http://img4.cache.netease.com/photo/0031/2017-03-02/CEHOM0SO6LRK0031.jpg", "http://img3.cache.netease.com/photo/0031/2017-03-02/CEHOM0UM6LRK0031.jpg", "http://img4.cache.netease.com/photo/0031/2017-03-02/CEHOM1176LRK0031.jpg"],
        "clientcover1": "",
        "replynum": "5",
        "topicname": "",
        "setid": "92597",
        "seturl": "http://play.163.com/photoview/6LRK0031/92597.html",
        "datetime": "2017-03-02 17:09:24",
        "clientcover": "",
        "imgsum": "23",
        "tcover": "http://img4.cache.netease.com/photo/0031/2017-03-02/t_CEHOM0SO6LRK0031.jpg"
    }, {
        "desc": "在《守望先锋》中，小美因为近身无敌的属性和胖胖的身材，被人戏称为美妈。可是你们怎么能忘记，小美虽然长得胖，但是圆圆的很可爱啊。近日，韩国知名COS团体RZ就COS了圆乎乎的小美。身材极度还原，但是颜值比游戏中的小美还要高上几分。一起来看下吧。",
        "pvnum": "",
        "createdate": "2017-03-01 18:11:18",
        "scover": "http://img3.cache.netease.com/photo/0031/2017-03-01/s_CEFA8KT76LRK0031.jpg",
        "setname": "冻住别走嘛~高颜值韩国妹子COS守望小美",
        "cover": "http://img4.cache.netease.com/photo/0031/2017-03-01/CEFA8KT76LRK0031.jpg",
        "pics": ["http://img4.cache.netease.com/photo/0031/2017-03-01/CEFA8KT76LRK0031.jpg", "http://img3.cache.netease.com/photo/0031/2017-03-01/CEFA8L1I6LRK0031.jpg", "http://img3.cache.netease.com/photo/0031/2017-03-01/CEFA8L3S6LRK0031.jpg"],
        "clientcover1": "",
        "replynum": "50",
        "topicname": "",
        "setid": "92583",
        "seturl": "http://play.163.com/photoview/6LRK0031/92583.html",
        "datetime": "2017-03-01 18:18:50",
        "clientcover": "",
        "imgsum": "24",
        "tcover": "http://img4.cache.netease.com/photo/0031/2017-03-01/t_CEFA8KT76LRK0031.jpg"
    }, {
        "desc": "小编新发现一组集合各大漫和游戏中的人物COS秀，个个亮眼，既有阴阳师里的姑获鸟，也有暗黑3里的武僧，造型各异，各具魅力。",
        "pvnum": "",
        "createdate": "2017-03-01 17:38:37",
        "scover": "http://img3.cache.netease.com/photo/0031/2017-03-01/s_CEF81D426LRK0031.jpeg",
        "setname": "还原游戏动漫场景 CosPlay赏析",
        "cover": "http://img4.cache.netease.com/photo/0031/2017-03-01/CEF81D426LRK0031.jpeg",
        "pics": ["http://img3.cache.netease.com/photo/0031/2017-03-01/CEF81D426LRK0031.jpeg", "http://img3.cache.netease.com/photo/0031/2017-03-01/CEF81D696LRK0031.jpeg", "http://img3.cache.netease.com/photo/0031/2017-03-01/CEF81D946LRK0031.jpeg"],
        "clientcover1": "",
        "replynum": "1",
        "topicname": "",
        "setid": "92579",
        "seturl": "http://play.163.com/photoview/6LRK0031/92579.html",
        "datetime": "2017-03-01 17:46:03",
        "clientcover": "",
        "imgsum": "48",
        "tcover": "http://img3.cache.netease.com/photo/0031/2017-03-01/t_CEF81D426LRK0031.jpeg"
    }, {
        "desc": "《魔兽世界》是一款老游戏了，所以品质精良的COS也不在少数。今天给大家带来的是一组，比精良还要精良的《魔兽世界》术士T5套装COS。这组COS来自波兰玩家stygianvi，还原度极高，特效堪称炸裂，更有趣的是这位小哥竟然自配魅魔，胸大腰细也是风情万种。",
        "pvnum": "",
        "createdate": "2017-02-28 18:16:58",
        "scover": "http://img4.cache.netease.com/photo/0031/2017-02-28/s_CECNSBDE6LRK0031.jpg",
        "setname": "WOW术士T5套装腐蚀者COS 颤抖吧凡人",
        "cover": "http://img4.cache.netease.com/photo/0031/2017-02-28/CECNSBDE6LRK0031.jpg",
        "pics": ["http://img3.cache.netease.com/photo/0031/2017-02-28/CECNSBDE6LRK0031.jpg", "http://img3.cache.netease.com/photo/0031/2017-02-28/CECNSBG86LRK0031.jpg", "http://img3.cache.netease.com/photo/0031/2017-02-28/CECNSBLT6LRK0031.jpg"],
        "clientcover1": "",
        "replynum": "5",
        "topicname": "",
        "setid": "92559",
        "seturl": "http://play.163.com/photoview/6LRK0031/92559.html",
        "datetime": "2017-02-28 18:18:37",
        "clientcover": "",
        "imgsum": "26",
        "tcover": "http://img4.cache.netease.com/photo/0031/2017-02-28/t_CECNSBDE6LRK0031.jpg"
    }]
}